README.md
setup.py
coffee_boat/__init__.py
coffee_boat/captain.py
coffee_boat/tests.py
coffee_boat.egg-info/PKG-INFO
coffee_boat.egg-info/SOURCES.txt
coffee_boat.egg-info/dependency_links.txt
coffee_boat.egg-info/top_level.txt