Metadata-Version: 1.0
Name: coffee-boat
Version: 0.0.1
Summary: Improve dependency management for PySpark in notebooks
Home-page: https://github.com/nteract/coffee_boat
Author: Holden Karau
Author-email: holden@pigscanfly.ca
License: LICENSE
Platform: UNKNOWN
